[
  {
    "id": "304200000013",
    "value": "15.34"
  },
  {
    "id": "304200000137",
    "value": "7.20"
  },
  {
    "id": "304200000153",
    "value": "13.25"
  },
  {
    "id": "304200000170",
    "value": "70.21"
  },
  {
    "id": "304200000188",
    "value": "70.71"
  },
  {
    "id": "304200000200",
    "value": "3.44"
  },
  {
    "id": "304200000218",
    "value": "28.76"
  },
  {
    "id": "304200000234",
    "value": "26.50"
  },
  {
    "id": "304200000242",
    "value": "32.29"
  },
  {
    "id": "304200000250",
    "value": "11.18"
  },
  {
    "id": "304200000269",
    "value": "78.20"
  },
  {
    "id": "304200000331",
    "value": "33.00"
  },
  {
    "id": "304200000382",
    "value": "9.00"
  },
  {
    "id": "304200000420",
    "value": "17.00"
  },
  {
    "id": "304200000439",
    "value": "29.80"
  },
  {
    "id": "304200000447",
    "value": "8.54"
  },
  {
    "id": "304200000455",
    "value": "11.12"
  },
  {
    "id": "304200000471",
    "value": "31.50"
  },
  {
    "id": "304200000501",
    "value": "70.71"
  },
  {
    "id": "304200000510",
    "value": "15.25"
  },
  {
    "id": "304200000560",
    "value": "21.50"
  },
  {
    "id": "304200000595",
    "value": "18.00"
  },
  {
    "id": "304200000609",
    "value": "40.02"
  },
  {
    "id": "304200000684",
    "value": "12.00"
  },
  {
    "id": "304200000706",
    "value": "31.00"
  },
  {
    "id": "304200000714",
    "value": "16.69"
  },
  {
    "id": "304200000722",
    "value": "30.98"
  },
  {
    "id": "304200000757",
    "value": "18.19"
  },
  {
    "id": "304200000900",
    "value": "27.60"
  },
  {
    "id": "304200001109",
    "value": "4.20"
  },
  {
    "id": "304200001117",
    "value": "5.82"
  },
  {
    "id": "304200001125",
    "value": "4.75"
  },
  {
    "id": "304200001133",
    "value": "9.21"
  },
  {
    "id": "304200002261",
    "value": "29.94"
  },
  {
    "id": "304200002300",
    "value": "29.98"
  },
  {
    "id": "304200002318",
    "value": "29.98"
  },
  {
    "id": "304200002474",
    "value": "11.30"
  },
  {
    "id": "304200002628",
    "value": "20.48"
  },
  {
    "id": "304200002741",
    "value": "1.50"
  },
  {
    "id": "304200002750",
    "value": "1.20"
  },
  {
    "id": "304200002768",
    "value": "2.77"
  },
  {
    "id": "304200002776",
    "value": "6.92"
  },
  {
    "id": "304200002792",
    "value": "5.70"
  },
  {
    "id": "304200002814",
    "value": "13.19"
  },
  {
    "id": "304200002822",
    "value": "8.85"
  },
  {
    "id": "304200002830",
    "value": "7.66"
  },
  {
    "id": "304200002849",
    "value": "16.72"
  },
  {
    "id": "304200003535",
    "value": "2.03"
  },
  {
    "id": "304200003578",
    "value": "4.98"
  },
  {
    "id": "304200003608",
    "value": "7.30"
  },
  {
    "id": "304200003632",
    "value": "9.82"
  },
  {
    "id": "304200004000",
    "value": "15.86"
  },
  {
    "id": "304200004051",
    "value": "7.20"
  },
  {
    "id": "304200004183",
    "value": "8.37"
  },
  {
    "id": "304200004230",
    "value": "40.57"
  },
  {
    "id": "304200004396",
    "value": "10.60"
  },
  {
    "id": "304200004434",
    "value": "19.53"
  },
  {
    "id": "304200004477",
    "value": "7.00"
  },
  {
    "id": "304200004612",
    "value": "24.56"
  },
  {
    "id": "304200004809",
    "value": "331.00"
  },
  {
    "id": "304200004850",
    "value": "23.23"
  },
  {
    "id": "304200004914",
    "value": "10.65"
  },
  {
    "id": "304200004957",
    "value": "8.72"
  },
  {
    "id": "304200005015",
    "value": "13.50"
  },
  {
    "id": "304200005074",
    "value": "42.00"
  },
  {
    "id": "304200005139",
    "value": "13.90"
  },
  {
    "id": "304200005368",
    "value": "19.43"
  },
  {
    "id": "304200005651",
    "value": "9.60"
  },
  {
    "id": "304200005880",
    "value": "9.05"
  },
  {
    "id": "304200005902",
    "value": "8.94"
  },
  {
    "id": "304200005988",
    "value": "7.33"
  },
  {
    "id": "304200006020",
    "value": "15.10"
  },
  {
    "id": "304200006046",
    "value": "76.00"
  },
  {
    "id": "304200006348",
    "value": "238.00"
  },
  {
    "id": "304200006402",
    "value": "6.00"
  },
  {
    "id": "304200006429",
    "value": "17.89"
  },
  {
    "id": "304200006470",
    "value": "48.73"
  },
  {
    "id": "304200006526",
    "value": "136.75"
  },
  {
    "id": "304200006550",
    "value": "18.90"
  },
  {
    "id": "304200006607",
    "value": "4.99"
  },
  {
    "id": "304200006615",
    "value": "7.00"
  },
  {
    "id": "304200006623",
    "value": "1.56"
  },
  {
    "id": "304200006640",
    "value": "7.98"
  },
  {
    "id": "304200006704",
    "value": "21.47"
  },
  {
    "id": "304200006712",
    "value": "10.77"
  },
  {
    "id": "304200006739",
    "value": "31.27"
  },
  {
    "id": "304200006763",
    "value": "6.79"
  },
  {
    "id": "304200006771",
    "value": "84.60"
  },
  {
    "id": "304200006780",
    "value": "13.80"
  },
  {
    "id": "304200006836",
    "value": "3.25"
  },
  {
    "id": "304200006860",
    "value": "25.00"
  },
  {
    "id": "304200007212",
    "value": "19.87"
  },
  {
    "id": "304200007670",
    "value": "4.70"
  },
  {
    "id": "304200007735",
    "value": "11.87"
  },
  {
    "id": "304200007751",
    "value": "3.42"
  },
  {
    "id": "304200007760",
    "value": "6.80"
  },
  {
    "id": "304200007778",
    "value": "25.00"
  },
  {
    "id": "304200007930",
    "value": "1.72"
  },
  {
    "id": "304200007956",
    "value": "35.00"
  },
  {
    "id": "304200007964",
    "value": "1.70"
  },
  {
    "id": "304200008057",
    "value": "6.51"
  },
  {
    "id": "304200008120",
    "value": "6.00"
  },
  {
    "id": "304200020353",
    "value": "3.20"
  },
  {
    "id": "304200020361",
    "value": "4.37"
  },
  {
    "id": "304200020373",
    "value": "4.40"
  },
  {
    "id": "304200020381",
    "value": "3.53"
  },
  {
    "id": "304200020393",
    "value": "4.25"
  },
  {
    "id": "304200020400",
    "value": "5.59"
  },
  {
    "id": "304200020412",
    "value": "0.80"
  },
  {
    "id": "304200020432",
    "value": "1.23"
  },
  {
    "id": "304200020440",
    "value": "4.76"
  },
  {
    "id": "304200020460",
    "value": "18.70"
  },
  {
    "id": "304200020472",
    "value": "19.00"
  },
  {
    "id": "304200020531",
    "value": "9.66"
  },
  {
    "id": "304200020943",
    "value": "25.40"
  },
  {
    "id": "304200020951",
    "value": "17.43"
  },
  {
    "id": "304200020963",
    "value": "7.40"
  },
  {
    "id": "304200021143",
    "value": "36.51"
  },
  {
    "id": "304200021222",
    "value": "25.97"
  },
  {
    "id": "304200021393",
    "value": "9.55"
  },
  {
    "id": "304200021460",
    "value": "19.82"
  },
  {
    "id": "304200021523",
    "value": "3.58"
  },
  {
    "id": "304200021543",
    "value": "25.23"
  },
  {
    "id": "304200021563",
    "value": "21.56"
  },
  {
    "id": "304200021610",
    "value": "5.10"
  },
  {
    "id": "304200021690",
    "value": "3.74"
  },
  {
    "id": "304200021721",
    "value": "1.52"
  },
  {
    "id": "304200021744",
    "value": "2.48"
  },
  {
    "id": "304200021749",
    "value": "19.00"
  },
  {
    "id": "304200021756",
    "value": "6.20"
  },
  {
    "id": "304200021757",
    "value": "35.12"
  },
  {
    "id": "304200021760",
    "value": "15.00"
  },
  {
    "id": "304200021762",
    "value": "16.06"
  },
  {
    "id": "304200021782",
    "value": "6.00"
  },
  {
    "id": "304200021783",
    "value": "13.44"
  },
  {
    "id": "304200021786",
    "value": "48.00"
  },
  {
    "id": "3042000000001",
    "value": "1.98"
  },
  {
    "id": "3042000000002",
    "value": "0.32"
  },
  {
    "id": "3042000000016",
    "value": "8.00"
  },
  {
    "id": "3042000000020",
    "value": "489.00"
  },
  {
    "id": "3042000000054",
    "value": "25.25"
  },
  {
    "id": "3042000000055",
    "value": "18.33"
  },
  {
    "id": "3042000000056",
    "value": "12.50"
  },
  {
    "id": "3042000000057",
    "value": "13.97"
  },
  {
    "id": "3042000000058",
    "value": "15.80"
  },
  {
    "id": "3042000000060",
    "value": "27.70"
  },
  {
    "id": "3042000000064",
    "value": "15.13"
  },
  {
    "id": "3042000000065",
    "value": "12.00"
  },
  {
    "id": "3042000000076",
    "value": "72.21"
  },
  {
    "id": "3042000000090",
    "value": "10.30"
  },
  {
    "id": "3042000000097",
    "value": "13.91"
  },
  {
    "id": "3042000000101",
    "value": "34.49"
  },
  {
    "id": "3042000000126",
    "value": "7.00"
  },
  {
    "id": "3042000000128",
    "value": "38.90"
  },
  {
    "id": "3042000000129",
    "value": "44.17"
  },
  {
    "id": "3042000000130",
    "value": "53.71"
  },
  {
    "id": "3042000000131",
    "value": "68.77"
  },
  {
    "id": "3042000000132",
    "value": "103.11"
  },
  {
    "id": "3042000000133",
    "value": "119.50"
  },
  {
    "id": "3042000000134",
    "value": "40.00"
  },
  {
    "id": "3042000000135",
    "value": "40.00"
  },
  {
    "id": "3042000000136",
    "value": "50.00"
  },
  {
    "id": "3042000000137",
    "value": "90.00"
  },
  {
    "id": "3042000000138",
    "value": "105.00"
  },
  {
    "id": "3042000000139",
    "value": "43.55"
  },
  {
    "id": "3042000000140",
    "value": "55.16"
  },
  {
    "id": "3042000000141",
    "value": "54.92"
  },
  {
    "id": "3042000000142",
    "value": "75.74"
  },
  {
    "id": "3042000000143",
    "value": "128.76"
  },
  {
    "id": "3042000000144",
    "value": "202.33"
  },
  {
    "id": "3042000000145",
    "value": "112.03"
  },
  {
    "id": "3042000000146",
    "value": "24.70"
  },
  {
    "id": "3042000000147",
    "value": "10.63"
  },
  {
    "id": "3042000000148",
    "value": "20.20"
  },
  {
    "id": "3042000000149",
    "value": "37.95"
  },
  {
    "id": "3042000000157",
    "value": "4.15"
  },
  {
    "id": "3042000000158",
    "value": "7.34"
  },
  {
    "id": "3042000000159",
    "value": "14.18"
  },
  {
    "id": "3042000000160",
    "value": "9.80"
  },
  {
    "id": "3042000000166",
    "value": "39.19"
  },
  {
    "id": "3042000000167",
    "value": "99.00"
  },
  {
    "id": "3042000000180",
    "value": "159.87"
  },
  {
    "id": "3042000000196",
    "value": "40.00"
  },
  {
    "id": "3042000000198",
    "value": "169.57"
  },
  {
    "id": "3042000000200",
    "value": "70.70"
  },
  {
    "id": "3042000000201",
    "value": "65.00"
  },
  {
    "id": "3042000000202",
    "value": "3.98"
  },
  {
    "id": "3042000000204",
    "value": "12.00"
  },
  {
    "id": "3042000000209",
    "value": "13.49"
  },
  {
    "id": "3042000000212",
    "value": "19.90"
  },
  {
    "id": "3042000000214",
    "value": "38.46"
  },
  {
    "id": "3042000000232",
    "value": "9.49"
  },
  {
    "id": "3042000000238",
    "value": "350.00"
  },
  {
    "id": "3042000000257",
    "value": "4.23"
  },
  {
    "id": "3042000000258",
    "value": "5.51"
  },
  {
    "id": "3042000000259",
    "value": "2.80"
  },
  {
    "id": "3042000000260",
    "value": "2.40"
  },
  {
    "id": "3042000000261",
    "value": "20.78"
  },
  {
    "id": "3042000000262",
    "value": "6.90"
  },
  {
    "id": "3042000000263",
    "value": "128.42"
  },
  {
    "id": "3042000000264",
    "value": "110.36"
  },
  {
    "id": "3042000000265",
    "value": "122.97"
  },
  {
    "id": "3042000000266",
    "value": "117.29"
  },
  {
    "id": "3042000000267",
    "value": "121.31"
  },
  {
    "id": "3042000000268",
    "value": "153.32"
  },
  {
    "id": "3042000000269",
    "value": "168.42"
  },
  {
    "id": "3042000000270",
    "value": "172.25"
  },
  {
    "id": "3042000000271",
    "value": "192.78"
  },
  {
    "id": "3042000000272",
    "value": "173.78"
  },
  {
    "id": "3042000000273",
    "value": "210.39"
  },
  {
    "id": "3042000000274",
    "value": "130.45"
  },
  {
    "id": "3042000000275",
    "value": "217.43"
  },
  {
    "id": "3042000000276",
    "value": "253.09"
  },
  {
    "id": "3042000000277",
    "value": "242.49"
  },
  {
    "id": "3042000000278",
    "value": "315.23"
  },
  {
    "id": "3042000000279",
    "value": "191.90"
  },
  {
    "id": "3042000000280",
    "value": "315.39"
  },
  {
    "id": "3042000000281",
    "value": "210.37"
  },
  {
    "id": "3042000000282",
    "value": "354.50"
  },
  {
    "id": "3042000000283",
    "value": "126.05"
  },
  {
    "id": "3042000000284",
    "value": "120.26"
  },
  {
    "id": "3042000000285",
    "value": "212.42"
  },
  {
    "id": "3042000000286",
    "value": "408.65"
  },
  {
    "id": "3042000000287",
    "value": "333.78"
  },
  {
    "id": "3042000000288",
    "value": "380.83"
  },
  {
    "id": "3042000000289",
    "value": "6.53"
  },
  {
    "id": "3042000000290",
    "value": "3.40"
  },
  {
    "id": "3042000000291",
    "value": "6.60"
  },
  {
    "id": "3042000000292",
    "value": "18.40"
  },
  {
    "id": "3042000000293",
    "value": "32.37"
  },
  {
    "id": "3042000000294",
    "value": "52.40"
  },
  {
    "id": "3042000000295",
    "value": "56.09"
  },
  {
    "id": "3042000000296",
    "value": "235.33"
  },
  {
    "id": "3042000000322",
    "value": "33.90"
  },
  {
    "id": "3042000000323",
    "value": "80.00"
  },
  {
    "id": "3042000000324",
    "value": "48.50"
  },
  {
    "id": "3042000000325",
    "value": "87.00"
  },
  {
    "id": "3042000000327",
    "value": "229.90"
  },
  {
    "id": "3042000000329",
    "value": "18.50"
  },
  {
    "id": "3042000000330",
    "value": "48.60"
  },
  {
    "id": "3042000000331",
    "value": "62.00"
  },
  {
    "id": "3042000000332",
    "value": "212.00"
  },
  {
    "id": "3042000000333",
    "value": "207.33"
  },
  {
    "id": "3042000000334",
    "value": "40.07"
  },
  {
    "id": "3042000000335",
    "value": "49.67"
  },
  {
    "id": "3042000000336",
    "value": "4.48"
  },
  {
    "id": "3042000000337",
    "value": "80.92"
  },
  {
    "id": "3042000000338",
    "value": "28.63"
  },
  {
    "id": "3042000000339",
    "value": "35.87"
  },
  {
    "id": "3042000000340",
    "value": "22.56"
  },
  {
    "id": "3042000000341",
    "value": "40.30"
  },
  {
    "id": "3042000000342",
    "value": "12.59"
  },
  {
    "id": "3042000000343",
    "value": "60.00"
  },
  {
    "id": "3042000000344",
    "value": "1.62"
  },
  {
    "id": "3042000000346",
    "value": "274.31"
  },
  {
    "id": "3042000000347",
    "value": "284.01"
  },
  {
    "id": "3042000000351",
    "value": "535.44"
  },
  {
    "id": "3042000000352",
    "value": "3.40"
  },
  {
    "id": "3042000000353",
    "value": "3.75"
  },
  {
    "id": "3042000000354",
    "value": "3.37"
  },
  {
    "id": "3042000000355",
    "value": "38.90"
  },
  {
    "id": "3042000000358",
    "value": "29.83"
  },
  {
    "id": "3042000000359",
    "value": "46.29"
  },
  {
    "id": "3042000000360",
    "value": "154.01"
  },
  {
    "id": "3042000000361",
    "value": "155.27"
  },
  {
    "id": "3042000000362",
    "value": "45.14"
  },
  {
    "id": "3042000000363",
    "value": "157.75"
  },
  {
    "id": "3042000000364",
    "value": "214.73"
  },
  {
    "id": "3042000000365",
    "value": "18.63"
  },
  {
    "id": "3042000000366",
    "value": "188.91"
  },
  {
    "id": "3042000000367",
    "value": "24.54"
  },
  {
    "id": "3042000000368",
    "value": "2236.21"
  },
  {
    "id": "3042000000369",
    "value": "93.14"
  },
  {
    "id": "3042000000370",
    "value": "37.15"
  },
  {
    "id": "3042000000371",
    "value": "18.59"
  },
  {
    "id": "3042000000372",
    "value": "21.70"
  },
  {
    "id": "3042000000373",
    "value": "23.52"
  },
  {
    "id": "3042000000374",
    "value": "79.02"
  },
  {
    "id": "3042000000375",
    "value": "225.95"
  },
  {
    "id": "3042000000376",
    "value": "80.49"
  },
  {
    "id": "3042000000377",
    "value": "52.66"
  },
  {
    "id": "3042000000378",
    "value": "48.08"
  },
  {
    "id": "3042000000379",
    "value": "46.88"
  },
  {
    "id": "3042000000380",
    "value": "42.27"
  },
  {
    "id": "3042000000381",
    "value": "108.74"
  },
  {
    "id": "3042000000383",
    "value": "299.99"
  },
  {
    "id": "3042000000384",
    "value": "6.51"
  },
  {
    "id": "3042000000385",
    "value": "9.21"
  },
  {
    "id": "3042000000386",
    "value": "130.97"
  },
  {
    "id": "3042000000387",
    "value": "224.51"
  },
  {
    "id": "3042000000388",
    "value": "79.56"
  },
  {
    "id": "3042000000389",
    "value": "82.60"
  },
  {
    "id": "3042000000390",
    "value": "79.56"
  },
  {
    "id": "3042000000391",
    "value": "56.67"
  },
  {
    "id": "3042000000392",
    "value": "51.53"
  },
  {
    "id": "3042000000393",
    "value": "90.20"
  }
 ]